pepino/__init__.py
pepino-0.1.2.dist-info/LICENSE
pepino-0.1.2.dist-info/WHEEL
pepino-0.1.2.dist-info/METADATA
pepino-0.1.2.dist-info/RECORD
