Metadata-Version: 2.1
Name: pepino
Version: 0.1.2
Summary: Esto no es mas que un lugar lleno de verdura
Home-page: https://github.com/akielbowicz/pepino
License: UNKNOWN
Author: sashakile
Author-email: saxa.kile@gmail.com
Classifier: License :: OSI Approved :: GNU General Public License v3 or later (GPLv3+)
